{
 "create_time": 1645120450,
 "observer": [
  475470952,
  864999295,
  1754030283
 ],
 "room": 431187625,
 "tables": {
  "先攻": {
   "KakyouinNoriaki": 2,
   "dodododoodododo": 15,
   "tes48": 16,
   "wq2": 19,
   "不阻挡": 2,
   "亚索": 1,
   "冷风": 5,
   "冼某": 5,
   "减1": 13,
   "减一": 18,
   "切不了合约虫子": 18,
   "加里奥": 16,
   "卢锡安": 16,
   "可汗": 11,
   "可汗出征": 6,
   "学弟": 5,
   "实名上网席德佳": 15,
   "寄吧迅亲爹": 14,
   "席德佳": 14,
   "席德佳 绝赞演出中！": 174,
   "徐某": 13,
   "扎克": 8,
   "拓拉": 5,
   "斯卡蒂": 17,
   "明灯": 10,
   "暖公子": 18,
   "暖哥哥": 6,
   "暖风": 19,
   "暖风亚索": 12,
   "林子": 17,
   "欺凌者": 12,
   "牛蒂蒂": 3,
   "特工": 5,
   "独行天途": 4,
   "红蒂": 15,
   "维克托": 2,
   "老八": 10015,
   "臭蒂蒂": 13,
   "苏茜sikadi": 16,
   "苏茜桑": 14,
   "蒂厨": 4,
   "蒂蒂": 6,
   "蓝蒂": 6,
   "薇薇安娜": 14,
   "这货不是暖风": 7,
   "阿卡丽": 11,
   "阿狸": 4,
   "雷公": 2,
   "音匀": 8,
   "香蒂蒂": 19
  }
 },
 "type": "simple",
 "update_time": 1648396954
}